jupytergis/__init__.py
jupytergis-0.11.1.dist-info/METADATA
jupytergis-0.11.1.dist-info/WHEEL
jupytergis-0.11.1.dist-info/licenses/LICENSE
jupytergis-0.11.1.dist-info/RECORD
