Metadata-Version: 2.4
Name: jupytergis
Version: 0.11.1
Summary: Collaborative GIS extension for JupyterLab
Project-URL: Homepage, https://github.com/geojupyter/jupytergis
Project-URL: Documentation, https://jupytergis.readthedocs.io
Project-URL: Repository, https://github.com/geojupyter/jupytergis.git
Project-URL: Issues, https://github.com/geojupyter/jupytergis/issues
License: BSD 3-Clause License
License-File: LICENSE
Classifier: Framework :: Jupyter
Classifier: Framework :: Jupyter :: JupyterLab
Classifier: Framework :: Jupyter :: JupyterLab :: 4
Classifier: Framework :: Jupyter :: JupyterLab :: Extensions
Classifier: Framework :: Jupyter :: JupyterLab :: Extensions :: Prebuilt
Classifier: License :: OSI Approved :: BSD License
Classifier: Programming Language :: Python
Classifier: Programming Language :: Python :: 3
Classifier: Programming Language :: Python :: 3.10
Classifier: Programming Language :: Python :: 3.11
Classifier: Programming Language :: Python :: 3.12
Classifier: Programming Language :: Python :: 3.13
Classifier: Programming Language :: Python :: 3.14
Classifier: Topic :: Scientific/Engineering :: GIS
Requires-Python: >=3.10
Requires-Dist: jupyter-collaboration-ui<3,>=2
Requires-Dist: jupyter-collaboration<5,>=4
Requires-Dist: jupyter-docprovider<3,>=2
Requires-Dist: jupyter-server-ydoc<3,>=2
Requires-Dist: jupytergis-core==0.11.1
Requires-Dist: jupytergis-lab==0.11.1
Requires-Dist: jupytergis-qgis==0.11.1
Requires-Dist: jupyterlab>=4.5.1
